quantforge-0.1.1.dist-info/METADATA
quantforge-0.1.1.dist-info/WHEEL
quantforge-0.1.1.dist-info/licenses/LICENSE
quantforge/__init__.py
quantforge/__init__.pyi
quantforge/models/__init__.py
quantforge/py.typed
quantforge/quantforge.abi3.so
quantforge/quantforge.pyi
quantforge-0.1.1.dist-info/RECORD
