Metadata-Version: 2.4
Name: quantforge
Version: 0.1.1
Classifier: Development Status :: 4 - Beta
Classifier: Intended Audience :: Developers
Classifier: Intended Audience :: Financial and Insurance Industry
Classifier: Intended Audience :: Science/Research
Classifier: License :: OSI Approved :: MIT License
Classifier: Programming Language :: Python :: 3
Classifier: Programming Language :: Python :: 3.12
Classifier: Programming Language :: Python :: 3.13
Classifier: Programming Language :: Python :: Implementation :: CPython
Classifier: Programming Language :: Rust
Classifier: Topic :: Office/Business :: Financial
Classifier: Topic :: Office/Business :: Financial :: Investment
Classifier: Topic :: Scientific/Engineering :: Mathematics
Classifier: Operating System :: OS Independent
Requires-Dist: numpy>=1.20
Requires-Dist: psutil>=7.0.0
Requires-Dist: pyarrow>=10.0.0
Requires-Dist: arro3-core>=0.4.0
Requires-Dist: pandas>=2.3.2
Requires-Dist: sphinx>=8.2.3 ; extra == 'docs'
Requires-Dist: sphinx-rtd-theme>=3.0.2 ; extra == 'docs'
Requires-Dist: myst-parser>=4.0.1 ; extra == 'docs'
Requires-Dist: linkify-it-py>=2.0.3 ; extra == 'docs'
Requires-Dist: sphinxext-opengraph>=0.9.1 ; extra == 'docs'
Requires-Dist: sphinxcontrib-mermaid>=1.0.0 ; extra == 'docs'
Requires-Dist: sphinx-copybutton>=0.5.2 ; extra == 'docs'
Requires-Dist: sphinx-tabs>=3.4.7 ; extra == 'docs'
Provides-Extra: docs
License-File: LICENSE
Summary: High-performance option pricing library powered by Rust + PyO3
Keywords: quantitative-finance,options,derivatives,black-scholes,option-pricing,financial-engineering,rust,high-performance
Author-email: driller <>
Maintainer-email: driller <>
Requires-Python: >=3.12
Project-URL: Homepage, https://github.com/drillan/quantforge
Project-URL: Documentation, https://github.com/drillan/quantforge/tree/main/docs
Project-URL: Repository, https://github.com/drillan/quantforge.git
Project-URL: Issues, https://github.com/drillan/quantforge/issues
Project-URL: Changelog, https://github.com/drillan/quantforge/blob/main/CHANGELOG.md
